<?xml version="1.0" encoding="UTF-8" standalone="no"?>
<!DOCTYPE log SYSTEM "logger.dtd">
<log>
<record>
  <date>2020-11-30T20:11:52.830395700Z</date>
  <millis>1606767112830</millis>
  <nanos>395700</nanos>
  <sequence>1</sequence>
  <logger>wikiMainhtml.class</logger>
  <level>INFO</level>
  <class>extracteur_java.wikiMainhtml</class>
  <method>extracteurenmarche</method>
  <thread>17</thread>
  <message>entering of the function which find tables by criteria</message>
</record>
<record>
  <date>2020-11-30T20:11:52.852363300Z</date>
  <millis>1606767112852</millis>
  <nanos>363300</nanos>
  <sequence>2</sequence>
  <logger>wikiMainhtml.class</logger>
  <level>INFO</level>
  <class>extracteur_java.wikiMainhtml</class>
  <method>extracteurenmarche</method>
  <thread>17</thread>
  <message>Loading..........</message>
</record>
<record>
  <date>2020-11-30T20:11:52.853369200Z</date>
  <millis>1606767112853</millis>
  <nanos>369200</nanos>
  <sequence>3</sequence>
  <logger>wikiMainhtml.class</logger>
  <level>INFO</level>
  <class>extracteur_java.wikiMainhtml</class>
  <method>extracteurenmarche</method>
  <thread>17</thread>
  <message>end of searching table by criteria</message>
</record>
<record>
  <date>2020-11-30T20:11:55.114053300Z</date>
  <millis>1606767115114</millis>
  <nanos>53300</nanos>
  <sequence>4</sequence>
  <logger>wikiMainhtml.class</logger>
  <level>FINER</level>
  <class>extracteur_java.wikiMainhtml</class>
  <method>getListofUrls</method>
  <thread>17</thread>
  <message>RETURN [extracteur_java.UrlMatrix@4b2b5811]</message>
</record>
<record>
  <date>2020-11-30T20:11:55.115927700Z</date>
  <millis>1606767115115</millis>
  <nanos>927700</nanos>
  <sequence>5</sequence>
  <logger>wikiMainhtml.class</logger>
  <level>INFO</level>
  <class>extracteur_java.wikiMainhtml</class>
  <method>extracteurenmarche</method>
  <thread>17</thread>
  <message>Extracting via html...</message>
</record>
</log>
